ytl/__init__.py
ytl/defaults.py
ytl/exceptions.py
ytl/options.py
ytl/standard_logistic_dims.py
ytl/unit_converters.py
ytl/utils.py
ytl/validation.py
ytl/logistics_objects/__init__.py
ytl/logistics_objects/common.py
ytl/logistics_objects/piece.py
ytl/logistics_objects/shipment.py
ytl/logistics_objects/trailer.py
ytl/optimizer_functions/__init__.py
ytl/optimizer_functions/piece_arrangement/__init__.py
ytl/optimizer_functions/piece_arrangement/greedy.py
ytl/optimizer_functions/piece_arrangement/naive.py
ytl/optimizer_functions/shipment_arrangement/__init__.py
ytl/optimizer_functions/shipment_arrangement/bin_packing.py
ytl/optimizer_functions/shipment_arrangement/greedy.py
ytl/optimizer_functions/shipment_arrangement/naive.py
ytl/optimizer_functions/shipment_arrangement/simple_movements.py
ytl/py3dbp/__init__.py
ytl/py3dbp/auxiliary_methods.py
ytl/py3dbp/constants.py
ytl/py3dbp/main.py
ytl/services/__init__.py
ytl/services/trailer_load.py
ytl/services/trailer_load_api.py
ytl-1.0.1.dist-info/LICENSE
ytl-1.0.1.dist-info/METADATA
ytl-1.0.1.dist-info/WHEEL
ytl-1.0.1.dist-info/top_level.txt
ytl-1.0.1.dist-info/zip-safe
ytl-1.0.1.dist-info/RECORD
