Metadata-Version: 2.1
Name: ytl
Version: 1.0.1
Summary: A fast trailer load optimization service provided by YAT, LLC
Author: Jarod Hart & Robert Goss
Author-email: Robert Goss <rgoss@yat.ai>, Jarod Hart <jhart@yat.ai>
License: MIT
Project-URL: Homepage, https://github.com/yat-co/yat-trailer-loading
Project-URL: Bug Tracker, https://github.com/yat-co/yat-trailer-loading/issues
Classifier: Programming Language :: Python :: 3
Classifier: License :: OSI Approved :: MIT License
Classifier: Operating System :: OS Independent
Requires-Python: >=3.7
License-File: LICENSE
Requires-Dist: numpy
Requires-Dist: matplotlib
